pydot_graph/__about__.py
pydot_graph/__init__.py
pydot_graph/pydot_graph.py
pydot_graph-0.0.4.dist-info/METADATA
pydot_graph-0.0.4.dist-info/WHEEL
pydot_graph-0.0.4.dist-info/licenses/LICENSE
pydot_graph-0.0.4.dist-info/RECORD
