Metadata-Version: 2.4
Name: pydot_graph
Version: 0.0.4
Summary: A graph notation for creating Graphviz visualizations using Pydot.
Project-URL: Homepage, https://github.com/faranalytics/pydot_graph
Project-URL: Bug Tracker, https://github.com/faranalytics/pydot_graph/issues
Author-email: Adam Patterson <adpatter@umich.edu>
License-File: LICENSE
Classifier: License :: OSI Approved :: MIT License
Classifier: Operating System :: OS Independent
Classifier: Programming Language :: Python :: 3
Requires-Python: >=3.9
Requires-Dist: pydot==2.*
